deltalake_ipython_extensions/__init__.py
deltalake_ipython_extensions/duckdb_extensions.py
deltalake_ipython_extensions-0.3.0.dist-info/METADATA
deltalake_ipython_extensions-0.3.0.dist-info/WHEEL
deltalake_ipython_extensions-0.3.0.dist-info/RECORD
