Metadata-Version: 2.1
Name: deltalake-ipython-extensions
Version: 0.3.0
Summary: 
Author: Your Name
Author-email: you@example.com
Requires-Python: >=3.8,<3.12
Classifier: Programming Language :: Python :: 3
Classifier: Programming Language :: Python :: 3.8
Classifier: Programming Language :: Python :: 3.9
Classifier: Programming Language :: Python :: 3.10
Classifier: Programming Language :: Python :: 3.11
Requires-Dist: deltalake (>=0.17.3)
Requires-Dist: duckdb (>=0.10.2)
Requires-Dist: ipython (>=8.0.0)
Requires-Dist: sqlparse (>=0.5.0)
